{
    "WQI": 51.507786155134134,
    "Dissolved Oxygen": 7.792353079627631,
    "pH": 7.453715551793637,
    "Conductivity": 394.09064957549117,
    "BOD": 0.8308474912445741,
    "Nitrate N + Nitrite N": -0.23933751093970823,
    "Fecal Coliform": -4.445791700746715,
    "Total Coliform": 5.699716885060411,
    "Location Name": "KHANDARI RESERVOIR WATER OFF TAKE POINT",
    "State Name": "MADHYA PRADESH",
    "lat": 23.8143419,
    "lon": 77.5340719,
    "processed_timestamp": "2024-11-27T09:58:09.208448"
}